phasepy-0.0.56.dist-info/WHEEL
phasepy-0.0.56.dist-info/top_level.txt
phasepy-0.0.56.dist-info/METADATA
phasepy-0.0.56.dist-info/RECORD
phasepy-0.0.56.dist-info/licenses/LICENSE.txt
phasepy/coloc_cy.cpython-39-x86_64-linux-gnu.so
phasepy/saft_forcefield.py
phasepy/coloc_cy.cpython-312-x86_64-linux-gnu.so
phasepy/coloc_cy.cpython-310-x86_64-linux-gnu.so
phasepy/constants.py
phasepy/math.py
phasepy/mixtures.py
phasepy/coloc_cy.cpython-311-x86_64-linux-gnu.so
phasepy/__init__.py
phasepy/cubic/vdwpure.py
phasepy/cubic/mhv1.py
phasepy/cubic/vtcubicmix.py
phasepy/cubic/vtcubicpure.py
phasepy/cubic/cubic.py
phasepy/cubic/mhv.py
phasepy/cubic/mixingrules.py
phasepy/cubic/cubicmix.py
phasepy/cubic/tsatpure.py
phasepy/cubic/cubicpure.py
phasepy/cubic/volume_solver.py
phasepy/cubic/qmr.py
phasepy/cubic/vdwmix.py
phasepy/cubic/psatpure.py
phasepy/cubic/wongsandler.py
phasepy/cubic/__init__.py
phasepy/cubic/alphas.py
phasepy/fit/binaryfit.py
phasepy/fit/fitpsat.py
phasepy/fit/fitvt.py
phasepy/fit/fitmulticomponent.py
phasepy/fit/fitcii.py
phasepy/fit/ternaryfit.py
phasepy/fit/__init__.py
phasepy/sgt/coloc_z.py
phasepy/sgt/sgtpure.py
phasepy/sgt/linear_spot.py
phasepy/sgt/path_sk.py
phasepy/sgt/cijmix_cy.cpython-312-x86_64-linux-gnu.so
phasepy/sgt/reference_component.py
phasepy/sgt/path_hk.py
phasepy/sgt/cijmix_cy.cpython-310-x86_64-linux-gnu.so
phasepy/sgt/cijmix_cy.cpython-311-x86_64-linux-gnu.so
phasepy/sgt/cijmix_cy.cpython-39-x86_64-linux-gnu.so
phasepy/sgt/tensionresult.py
phasepy/sgt/coloc_z_ds.py
phasepy/sgt/__init__.py
phasepy/sgt/sgt_beta0.py
phasepy/database/dortmund-2021.xlsx
phasepy/database/dortmund-2018.xlsx
phasepy/database/original-unifac.xlsx
phasepy/database/unifac.xlsx
phasepy/equilibrium/lle.py
phasepy/equilibrium/equilibriumresult.py
phasepy/equilibrium/dew.py
phasepy/equilibrium/flash.py
phasepy/equilibrium/solidequilibria.py
phasepy/equilibrium/stability.py
phasepy/equilibrium/bubble.py
phasepy/equilibrium/multiflash.py
phasepy/equilibrium/__init__.py
phasepy/equilibrium/hazb.py
phasepy/equilibrium/hazt.py
phasepy/src/actmodels_cy.c
phasepy/src/coloc_cy.c
