Metadata-Version: 2.4
Name: phasepy
Version: 0.0.56
Summary: Multiphase multicomponent Equilibria
Author: Andres Mejia Matallana
Author-email: Gustavo Chaparro <gchaparro@ethz.ch>
License: MIT
Project-URL: Homepage, https://github.com/gustavochm/phasepy
Project-URL: Download, https://github.com/gustavochm/phasepy.git
Keywords: Phase Equilibrium,Cubic EOS,QMR,MHV,WS,NRTL,Wilson,UNIFAC,UNIQUAC,Flash,VLE,LLE,VLLE,SGT
Requires-Python: >=3.9
License-File: LICENSE.txt
Requires-Dist: numpy>=2.0.0
Requires-Dist: scipy>=1.13
Requires-Dist: pandas>=2.2
Requires-Dist: openpyxl>=3.0.0
Provides-Extra: dev
Requires-Dist: cython>=3.0; extra == "dev"
Requires-Dist: pytest>=6.0; extra == "dev"
Requires-Dist: build; extra == "dev"
Dynamic: license-file
